min2tray.py
min2tray-0.1.1.dist-info/METADATA
min2tray-0.1.1.dist-info/WHEEL
min2tray-0.1.1.dist-info/entry_points.txt
min2tray-0.1.1.dist-info/top_level.txt
min2tray-0.1.1.dist-info/RECORD
