Metadata-Version: 2.1
Name: min2tray
Version: 0.1.1
Summary: Minimize program to system tray
Home-page: https://github.com/gzj/min2tray
Author: gzj
Author-email: gzj00@outlook.com
Requires-Dist: pystray
Requires-Dist: pynput
Requires-Dist: Pillow
